{"docId":1189,"title":"Computer hardware","body":"Computer hardware includes the physical parts of a computer, such as the central processing unit (CPU), random-access memory (RAM), motherboard, computer data storage, graphics card, sound card, and computer case. It includes external devices such as a monitor, mouse, keyboard, and speakers.\nBy contrast, software is a set of written instructions that can be stored and run by hardware. Hardware derived its name from the fact that it is hard or rigid with respect to changes, whereas software is soft because it is easy to change.\nHardware is typically directed by the software to execute any command or instruction. A combination of hardware and software forms a usable computing system, although other systems exist with only hardware.","categories":["All Wikipedia articles written in American English","All articles with unsourced statements","Articles with short description","Articles with unsourced statements from August 2024","CS1: unfit URL","Commons category link from Wikidata","Computer hardware","Digital electronics","Short description matches Wikidata","Use American English from November 2023","Use dmy dates from March 2017"],"url":"https://en.wikipedia.org/wiki/Computer_hardware"}