{"docId":1464,"title":"BCSWomen","body":"BCSWomen is a Specialist Group of the British Computer Society, The Chartered Institute for IT, that provides networking opportunities for all BCS professional women working in IT around the world, as well as mentoring and encouraging girls and women to enter or return to IT as a career.  The current Chair of BCSWomen is Andrea Palmer.","categories":["All Wikipedia articles written in British English","Articles with short description","BCS Specialist Groups","Information technology organisations based in the United Kingdom","Non-profit organisations based in the United Kingdom","Organizations established in 2001","Organizations for women in science and technology","Short description matches Wikidata","Use British English from February 2015","Use dmy dates from February 2015","Webarchive template wayback links","Women's organisations based in the United Kingdom"],"url":"https://en.wikipedia.org/wiki/BCSWomen"}