{"docId":1760,"title":"Real and nominal value","body":"In economics, nominal value refers to value measured in terms of absolute money amounts, whereas real value is considered and measured against the actual goods or services for which it can be exchanged at a given time. Real value takes into account inflation and the value of an asset in relation to its purchasing power. In macroeconomics, the real gross domestic product compensates for inflation so economists can exclude inflation from growth figures, and see how much an economy actually grows. Nominal GDP would include inflation, and thus be higher.","categories":["Articles with excerpts","Articles with short description","Inflation","Short description is different from Wikidata","Valuation (finance)"],"url":"https://en.wikipedia.org/wiki/Real_and_nominal_value"}