{"docId":1792,"title":"Belousov–Zhabotinsky reaction","body":"A Belousov–Zhabotinsky reaction, or BZ reaction, is one of a class of reactions that serve as a classical example of non-equilibrium thermodynamics, resulting in the establishment of a nonlinear chemical oscillator. The only common element in these oscillators is the inclusion of bromine and an acid. The reactions are important to theoretical chemistry in that they show that chemical reactions do not have to be dominated by equilibrium thermodynamic behavior. These reactions are far from equilibrium  and remain so for a significant length of time and evolve chaotically. In this sense, they provide an interesting chemical model of nonequilibrium biological  phenomena; as such, mathematical models and simulations of the BZ reactions themselves are of theoretical interest, showing phenomenon as noise-induced order.\n\nAn essential aspect of the BZ reaction is its so called \"excitability\"; under the influence of stimuli, patterns develop in what would otherwise be a perfectly quiescent medium. Some clock reactions such as Briggs–Rauscher and BZ using tris(bipyridine)ruthenium(II) chloride as a catalyst can be excited into self-organising activity through the influence of light.","categories":["All articles with dead external links","All articles with unsourced statements","Articles with dead external links from October 2016","Articles with permanently dead external links","Articles with short description","Articles with unsourced statements from November 2024","Clock reactions","Commons link from Wikidata","Name reactions","Non-equilibrium thermodynamics","Pattern formation","Short description is different from Wikidata"],"url":"https://en.wikipedia.org/wiki/Belousov%E2%80%93Zhabotinsky_reaction"}