{"docId":1935,"title":"Hope (programming language)","body":"Hope is a programming language based on functional programming developed in the 1970s at the University of Edinburgh.\nIt predates Miranda and Haskell and is contemporaneous with ML, also developed at the university. Hope was derived from NPL, a simple functional language developed by Rod Burstall and John Darlington in their work on program transformation. NPL and Hope are notable for being the first languages with call-by-pattern evaluation and algebraic data types.\nHope was named for Sir Thomas Hope (c. 1681–1771), a Scottish agriculture reformer, after whom Hope Park Square in Edinburgh, the location of the artificial intelligence department at the time of the development of Hope, was also named.\nThe first implementation of Hope used strict evaluation, but there have since been lazy evaluation versions and strict versions with lazy constructors. A successor language Hope+, developed jointly between Imperial College and International Computers Limited, added annotations to dictate either strict or lazy evaluation.","categories":["Academic programming languages","Articles with example code","Articles with short description","CS1 maint: location missing publisher","Functional languages","History of computing in the United Kingdom","Short description matches Wikidata","Statically typed programming languages","University of Edinburgh"],"url":"https://en.wikipedia.org/wiki/Hope_(programming_language)"}