{"docId":2443,"title":"History of general-purpose CPUs","body":"The history of general-purpose CPUs is a continuation of the earlier history of computing hardware.","categories":["All articles needing additional references","All articles that may contain original research","All articles with unsourced statements","Articles needing additional references from March 2009","Articles that may contain original research from March 2009","Articles with multiple maintenance issues","Articles with short description","Articles with unsourced statements from April 2017","Articles with unsourced statements from May 2022","Central processing unit","History of computing","History of computing hardware","Short description is different from Wikidata"],"url":"https://en.wikipedia.org/wiki/History_of_general-purpose_CPUs"}