{"docId":2611,"title":"Hardware backdoor","body":"A hardware backdoor is a backdoor implemented within the physical components of a computer system, also known as its hardware. They can be created by introducing malicious code to a component's firmware, or even during the manufacturing process of an integrated circuit. Often, they are used to undermine security in smartcards and cryptoprocessors, unless investment is made in anti-backdoor design methods. They have also been considered for car hacking.\nBackdoors differ from hardware Trojans as backdoors are introduced intentionally by the original designer or during the design process, whereas hardware Trojans are inserted later by an external party.","categories":["All articles to be expanded","Articles to be expanded from January 2017","Articles with short description","CS1 German-language sources (de)","Computer hardware","Cryptographic attacks","Cyberwarfare","Espionage techniques","Malware","Short description matches Wikidata","Surveillance"],"url":"https://en.wikipedia.org/wiki/Hardware_backdoor"}