{"docId":3389,"title":"Continuum hypothesis","body":"In mathematics, specifically set theory, the continuum hypothesis (abbreviated CH) is a hypothesis about the possible sizes of infinite sets. It states:\n\nThere is no set whose cardinality is strictly between that of the integers and the real numbers. The name of the hypothesis comes from the term continuum for the real numbers. In Zermelo–Fraenkel set theory with the axiom of choice (ZFC), this is equivalent to the following equation in aleph numbers: \n  \n    \n      \n        \n          2\n          \n            \n              ℵ\n              \n                0\n              \n            \n          \n        \n        =\n        \n          ℵ\n          \n            1\n          \n        \n      \n    \n    {\\displaystyle 2^{\\aleph _{0}}=\\aleph _{1}}\n  \n, or even shorter with beth numbers: \n  \n    \n      \n        \n          ℶ\n          \n            1\n          \n        \n        =\n        \n          ℵ\n          \n            1\n          \n        \n      \n    \n    {\\displaystyle \\beth _{1}=\\aleph _{1}}\n  \n.\nThe continuum hypothesis was advanced by Georg Cantor in 1878. It became one of the most studied problems in set theory, and establishing its truth or falsehood was the first of Hilbert's 23 problems presented in 1900. The answer to this problem is independent of ZFC. This means the axioms of ZFC can neither prove nor disprove the continuum hypothesis, meaning either the continuum hypothesis or its negation can be added as an axiom to ZFC set theory, with the resulting theory being consistent if and only if ZFC is consistent. This independence was proved in 1963 by Paul Cohen, complementing earlier work by Kurt Gödel in 1940.\nThe generalized continuum hypothesis states that \n  \n    \n      \n        \n          ℵ\n          \n            α\n            +\n            1\n          \n        \n        =\n        \n          2\n          \n            \n              ℵ\n              \n                α\n              \n            \n          \n        \n      \n    \n    {\\displaystyle \\aleph _{\\alpha +1}=2^{\\aleph _{\\alpha }}}\n  \n for every ordinal \n  \n    \n      \n        α\n      \n    \n    {\\displaystyle \\alpha }\n  \n.","categories":["Articles with short description","Basic concepts in infinite set theory","CS1 German-language sources (de)","CS1 maint: DOI inactive as of December 2025","Cardinal numbers","Forcing (mathematics)","Hilbert's problems","Hypotheses","Independence results","Infinity","Short description is different from Wikidata","Use shortened footnotes from May 2021","Webarchive template wayback links","Wikipedia articles incorporating text from PlanetMath"],"url":"https://en.wikipedia.org/wiki/Continuum_hypothesis"}