{"docId":3735,"title":"Absolute value","body":"In mathematics, the absolute value or modulus of a real number \n  \n    \n      \n        x\n      \n    \n    {\\displaystyle x}\n  \n, denoted \n  \n    \n      \n        \n          |\n        \n        x\n        \n          |\n        \n      \n    \n    {\\displaystyle |x|}\n  \n, is the (non-negative) magnitude of \n  \n    \n      \n        x\n      \n    \n    {\\displaystyle x}\n  \n measured without regard to its sign. Namely, \n  \n    \n      \n        \n          |\n        \n        x\n        \n          |\n        \n        =\n        x\n      \n    \n    {\\displaystyle |x|=x}\n  \n if \n  \n    \n      \n        x\n      \n    \n    {\\displaystyle x}\n  \n is a positive number, and \n  \n    \n      \n        \n          |\n        \n        x\n        \n          |\n        \n        =\n        −\n        x\n      \n    \n    {\\displaystyle |x|=-x}\n  \n if \n  \n    \n      \n        x\n      \n    \n    {\\displaystyle x}\n  \n is negative (in which case negating \n  \n    \n      \n        x\n      \n    \n    {\\displaystyle x}\n  \n makes \n  \n    \n      \n        −\n        x\n      \n    \n    {\\displaystyle -x}\n  \n positive), and \n  \n    \n      \n        \n          |\n        \n        0\n        \n          |\n        \n        =\n        0\n      \n    \n    {\\displaystyle |0|=0}\n  \n. For example, the absolute value of 3 is 3, and the absolute value of −3 is also 3. The absolute value of a number may be thought of as its distance from zero.\nGeneralisations of the absolute value for real numbers occur in a wide variety of mathematical settings. For example, an absolute value is also defined for the complex numbers, the quaternions, ordered rings, fields and vector spaces. The absolute value is closely related to the notions of magnitude, distance, and norm in various mathematical and physical contexts.","categories":["Articles with short description","Norms (mathematics)","Real numbers","Short description is different from Wikidata","Special functions","Use dmy dates from December 2020"],"url":"https://en.wikipedia.org/wiki/Absolute_value"}