{"docId":4289,"title":"Cambridge","body":"Cambridge (  KAYM-brij) is a city and non-metropolitan district in the county of Cambridgeshire, England. It is the county town of Cambridgeshire and is located on the River Cam, 55 miles (89 km) north of London. As of the 2021 United Kingdom census, the population of the City of Cambridge was 145,700; the population of the wider built-up area (which extends outside the city council area) was 181,137. There is archaeological evidence of settlement in the area dating back to as early as the Bronze Age, and Cambridge became an important trading centre during the Roman and Viking eras. The first town charters were granted in the 12th century, although modern city status was not officially conferred until 1951.\nThe city is well known as the home of the University of Cambridge, which was founded in 1209 and consistently ranks among the best universities in the world. The buildings of the university include King's College Chapel, Cavendish Laboratory, and the Cambridge University Library, one of the largest legal deposit libraries in the world. The city's skyline is dominated by several college buildings, along with the spire of the Our Lady and the English Martyrs Church, and the chimney of Addenbrooke's Hospital. Anglia Ruskin University, which evolved from the Cambridge School of Art and the Cambridgeshire College of Arts and Technology, also has its main campus in the city.\nCambridge is at the heart of the high-technology Silicon Fen also known as the  Cambridge Cluster, which contains industries such as software and bioscience and many start-up companies born out of the university. Over 40 per cent of the workforce have a higher education qualification, more than twice the national average. The Cambridge Biomedical Campus, one of the largest biomedical research clusters in the world, includes the headquarters of AstraZeneca and the relocated Royal Papworth Hospital.\nCambridge produced the first 'Laws of the Game' for association football and was the site of the first game, which was held at Parker's Piece. The Strawberry Fair music and art festival and Midsummer Fair are held on Midsummer Common, and the annual Cambridge Beer Festival takes place on Jesus Green. The city is adjacent to the M11 and A14 roads.","categories":["All Wikipedia articles written in British English","All articles containing potentially dated statements","All articles with dead external links","Articles containing Latin-language text","Articles containing potentially dated statements from November 2022","Articles tagged with the inline citation overkill template from July 2025","Articles with Latin-language sources (la)","Articles with dead external links from June 2016","Articles with dead external links from March 2018","Articles with permanently dead external links","Articles with short description","Boroughs in England","CS1:Vancouver names with accept markup","CS1: unfit URL","CS1 errors: ISBN date","CS1 maint: bot: original URL status unknown","CS1 maint: deprecated archival service","Cambridge","Citation overkill","Cities in the East of England"],"url":"https://en.wikipedia.org/wiki/Cambridge"}