{"docId":4697,"title":"Princeton University Press","body":"Princeton University Press is an independent nonprofit publisher closely affiliated with Princeton University. Founded in 1905, its mission is to disseminate scholarly ideas within academia and among the broader public. With over 10,000 titles in print, Princeton University Press publishes more than 300 new non-fiction books each year. It is headquartered in Princeton, NJ, with additional offices in Oxford, England, and Beijing, China. \nChristie Henry became the press' ninth director in 2017. Since then, the press has diversified its offerings to include audiobooks, a speakers’ bureau, and representation of other publishers' titles in China. In 2025, Princeton University Press acquired Island Press, a nonprofit publisher that focuses on environmental issues and the built environment.","categories":["1905 establishments in New Jersey","All Wikipedia articles written in American English","All articles needing additional references","Articles needing additional references from April 2026","Articles with multiple maintenance issues","Articles with short description","Book publishing companies based in New Jersey","CS1 French-language sources (fr)","Historic district contributing properties in Mercer County, New Jersey","Princeton University publications","Publishing companies established in 1905","Short description is different from Wikidata","University presses of the United States","Use American English from October 2023","Use mdy dates from October 2023"],"url":"https://en.wikipedia.org/wiki/Princeton_University_Press"}