{"docId":4809,"title":"Builders' rites","body":"Builders' rites are ceremonies attendant on the laying of foundation stones, including ecclesiastical, masonic or other traditions connected with foundations or other aspects of construction.\nOne such custom is that of placing a few coins, newspapers, etc. within a cavity beneath the stone. Should the stone later be removed, the relics may be found. Though this tradition is still practiced, such memorials are likely deposited in the hope that they will never be disturbed. Another such rite is topping out, when the last beam (or its equivalent) is placed atop a structure during its construction.","categories":["All articles with unsourced statements","Articles with short description","Articles with unsourced statements from January 2011","Building","Building engineering","Ceremonies","History of construction","Rituals attending construction","Short description is different from Wikidata","Use mdy dates from May 2024","Wikipedia articles incorporating a citation from the 1911 Encyclopaedia Britannica with Wikisource reference","Wikipedia articles incorporating text from the 1911 Encyclopædia Britannica"],"url":"https://en.wikipedia.org/wiki/Builders%27_rites"}