{"docId":4874,"title":"Algebraic geometry code","body":"Algebraic geometry codes, often abbreviated AG codes, are a type of linear code that generalize Reed–Solomon codes. The Russian mathematician V. D. Goppa constructed these codes for the first time in 1982.","categories":["Algebraic curves","Articles containing proofs","Articles with short description","Coding theory","Finite fields","Short description is different from Wikidata"],"url":"https://en.wikipedia.org/wiki/Algebraic_geometry_code"}