{"docId":5575,"title":"Ansatz","body":"In physics and mathematics, an ansatz (; German: [ˈʔanzats] , meaning: \"initial placement of a tool at a work piece\", plural ansatzes or, from German, ansätze ; German: [ˈʔanzɛtsə] ) is an educated guess or an additional assumption made to help solve a problem, and which may later be verified to be part of the solution by its results.","categories":["Articles with short description","Concepts in physics","Mathematical terminology","Pages including recorded pronunciations","Pages using the Phonos extension","Pages with German IPA","Philosophy of physics","Short description matches Wikidata"],"url":"https://en.wikipedia.org/wiki/Ansatz"}