{"docId":6012,"title":"Folk music","body":"Folk music is a music genre that includes traditional folk music and the contemporary genre that evolved from the former during the 20th-century folk revival. Some types of folk music may be called world music. Traditional folk music has been defined in several ways: as music transmitted orally, music with unknown composers, music that is played on traditional instruments, music about cultural or national identity, music that changes between generations (folk process), music associated with a people's folklore, or music performed by custom over a long period of time. It has been contrasted with commercial and classical styles. The term originated in the 19th century, but folk music extends beyond that.\nStarting in the mid-20th century, a new form of popular folk music evolved from traditional folk music. This process and period is called the (second) folk revival and reached a zenith in the 1960s. This form of music is sometimes called contemporary folk music or folk revival music to distinguish it from earlier folk forms. Smaller, similar revivals have occurred elsewhere in the world at other times, but the term folk music has typically not been applied to the new music created during those revivals. This type of folk music also includes fusion genres such as folk rock, folk metal, and others. While contemporary folk music is a genre generally distinct from traditional folk music, in U.S. English it shares the same name, and it often shares the same performers and venues as traditional folk music.","categories":["All articles needing additional references","All articles with dead external links","All articles with unsourced statements","Articles containing Spanish-language text","Articles containing video clips","Articles needing additional references from October 2022","Articles with Swedish-language sources (sv)","Articles with dead external links from April 2024","Articles with dead external links from February 2026","Articles with hAudio microformats","Articles with permanently dead external links","Articles with short description","Articles with unsourced statements from March 2026","Articles with unsourced statements from October 2021","Articles with unsourced statements from October 2022","CS1: unfit URL","CS1 Albanian-language sources (sq)","CS1 French-language sources (fr)","CS1 German-language sources (de)","CS1 maint: publisher location"],"url":"https://en.wikipedia.org/wiki/Folk_music"}