{"docId":6175,"title":"Cumulative distribution function","body":"In probability theory and statistics, the cumulative distribution function (CDF) of a real-valued random variable \n  \n    \n      \n        X\n      \n    \n    {\\displaystyle X}\n  \n, or just distribution function of \n  \n    \n      \n        X\n      \n    \n    {\\displaystyle X}\n  \n, evaluated at \n  \n    \n      \n        x\n      \n    \n    {\\displaystyle x}\n  \n, is the probability that \n  \n    \n      \n        X\n      \n    \n    {\\displaystyle X}\n  \n will take a value less than or equal to \n  \n    \n      \n        x\n      \n    \n    {\\displaystyle x}\n  \n.\nEvery probability distribution supported on the real numbers, discrete or \"mixed\" as well as continuous, is uniquely identified by a right-continuous monotone increasing function (a càdlàg function) \n  \n    \n      \n        F\n        :\n        \n          R\n        \n        →\n        [\n        0\n        ,\n        1\n        ]\n      \n    \n    {\\displaystyle F\\colon \\mathbb {R} \\rightarrow [0,1]}\n  \n satisfying \n  \n    \n      \n        \n          lim\n          \n            x\n            →\n            −\n            ∞\n          \n        \n        F\n        (\n        x\n        )\n        =\n        0\n      \n    \n    {\\displaystyle \\lim _{x\\rightarrow -\\infty }F(x)=0}\n  \n and \n  \n    \n      \n        \n          lim\n          \n            x\n            →\n            ∞\n          \n        \n        F\n        (\n        x\n        )\n        =\n        1\n      \n    \n    {\\displaystyle \\lim _{x\\rightarrow \\infty }F(x)=1}\n  \n.\nIn the case of a scalar continuous distribution, it gives the area under the probability density function from negative infinity to \n  \n    \n      \n        x\n      \n    \n    {\\displaystyle x}\n  \n. Cumulative distribution functions are also used to specify the distribution of multivariate random variables.","categories":["All articles needing additional references","All articles with unsourced statements","Articles needing additional references from March 2010","Articles with short description","Articles with unsourced statements from April 2012","Articles with unsourced statements from February 2021","CS1 maint: archived copy as title","Commons category link is on Wikidata","Functions related to probability distributions","Short description is different from Wikidata","Wikipedia articles needing clarification from March 2025","Wikipedia articles needing page number citations from June 2011"],"url":"https://en.wikipedia.org/wiki/Cumulative_distribution_function"}