{"docId":6308,"title":"American eccentric cinema","body":"American eccentric cinema is a mode of contemporary American filmmaking that emerged in what has been termed the metamodern or new sincerity. Its attachment to indie cinema has led some to consider it a movement and genre of cinema in the United States. Its key filmmakers, including Wes Anderson, Charlie Kaufman, and Spike Jonze, are at times referred to as the \"American Eccentrics\". It occurred during the 1990s and 2000s, when indie directors sought to create films that diverted from the style and content of Hollywood franchise films. American eccentric cinema came in opposition to the mainstream ideas of formulaic narratives and the digitisation within films and new technologies that came about during the time period. American eccentric cinema is marked by films that are \"deeply concerned with ethics and morality, the obligations of the individual, the effects of family breakdown, and social alienation.\"","categories":["1990s in film","2000s in film","2010s in film","Articles with short description","Articles with specifically marked weasel-worded phrases from December 2025","CS1 French-language sources (fr)","CS1 maint: location missing publisher","Eccentricity (behavior)","Film genres","Film genres particular to the United States","Postmodern art","Short description matches Wikidata"],"url":"https://en.wikipedia.org/wiki/American_eccentric_cinema"}