{"docId":6462,"title":"Auguste Comte","body":"Isidore Auguste Marie François Xavier Comte (; French: [oɡyst(ə) kɔ̃t] ; 19 January 1798 – 5 September 1857) was a French philosopher, mathematician and writer who formulated the doctrine of positivism. He is often regarded as the first philosopher of science in the modern sense of the term. Comte's ideas were fundamental to the development of sociology, with him inventing the very term and treating the discipline as the crowning achievement of the sciences.\nInfluenced by Henri de Saint-Simon, Comte's work attempted to remedy the social disorder caused by the French Revolution, which he believed indicated an imminent transition to a new form of society. He sought to establish a new social doctrine based on science, which he labeled positivism. He had a major impact on 19th-century thought, influencing the work of social thinkers such as John Stuart Mill and George Eliot. His concept of Sociology and social evolutionism set the tone for early social theorists and anthropologists such as Harriet Martineau and Herbert Spencer, evolving into modern academic sociology presented by Émile Durkheim as practical and objective social research.\nComte's social theories culminated in his \"Religion of Humanity\", which presaged the development of non-theistic religious humanist and secular humanist organizations in the 19th century. He may also have coined the word altruism.","categories":["1798 births","1857 deaths","19th-century French economists","19th-century French essayists","19th-century French male writers","19th-century French mathematicians","19th-century French philosophers","All articles with unsourced statements","Articles containing French-language text","Articles containing German-language text","Articles containing Latin-language text","Articles with Internet Archive links","Articles with LibriVox links","Articles with Project Gutenberg links","Articles with hCards","Articles with short description","Articles with unsourced statements from August 2011","Articles with unsourced statements from August 2019","Auguste Comte","Burials at Père Lachaise Cemetery"],"url":"https://en.wikipedia.org/wiki/Auguste_Comte"}