{"docId":6542,"title":"Food & Wine","body":"Food & Wine is an American monthly magazine published by People Inc.. It was founded in 1978 by Ariane and Michael Batterberry.  It features recipes, cooking tips, travel information, restaurant reviews, chefs, wine pairings and seasonal/holiday content and has been credited by The New York Times with introducing the dining public to \"Perrier, the purple Peruvian potato and Patagonian toothfish\".\nThe premier event for the magazine is the Food & Wine Classic in Aspen, Colorado. The Classic features wine tasting, cooking demonstrations, and featured speakers as well as a cooking competition. Held annually in June, the event is considered the kickoff to the Aspen summer season and celebrated its 40th anniversary in 2023.\nThe winner of Top Chef, the reality television cooking competition, is featured in a spread in this magazine.","categories":["Articles with short description","CS1 maint: deprecated archival service","Food and drink magazines published in the United States","IAC Inc.","Lifestyle magazines published in the United States","Magazines established in 1978","Magazines published in Alabama","Mass media in Birmingham, Alabama","Monthly magazines published in the United States","Official website different in Wikidata and Wikipedia","Short description is different from Wikidata","Use mdy dates from March 2025","Webarchive template wayback links","Wine magazines"],"url":"https://en.wikipedia.org/wiki/Food_%26_Wine"}