{"docId":6557,"title":"Lifewire","body":"Lifewire is a technology information and advice website. The website's owner is Dotdash Meredith, originally About.com, which launched Lifewire in 2016 as one of its spin-off vertical sites.\nAs of April 2022, it had a global website ranking of 1432 by Alexa Internet.","categories":["2016 establishments in the United States","American technology news websites","Articles with short description","Internet properties established in 2016","Short description is different from Wikidata","Technology websites","Use mdy dates from June 2023"],"url":"https://en.wikipedia.org/wiki/Lifewire"}