{"docId":6584,"title":"TechCrunch","body":"TechCrunch is an American global online newspaper focusing on topics regarding high-tech and startup companies. It was founded in June 2005 by Archimedes Ventures, led by partners Michael Arrington and Keith Teare. In 2010, AOL acquired the company for approximately $25 million. Following the 2015 acquisition of AOL and Yahoo! by Verizon, the site was owned by Verizon Media from 2015 through 2021.\nIn 2021, Verizon sold its media assets, including AOL, Yahoo!, and TechCrunch, to the private equity firm Apollo Global Management. Apollo integrated them into a new entity called Yahoo! Inc. In addition to its news reporting, TechCrunch is also known for its annual Disrupt conference, a technology event hosted in several cities across the United States, Europe, and China.","categories":["2005 establishments in the United States","2010 mergers and acquisitions","2017 mergers and acquisitions","2025 mergers and acquisitions","All Wikipedia articles written in American English","All articles containing potentially dated statements","American technology news websites","Articles containing potentially dated statements from 2013","Articles with Japanese-language sources (ja)","Articles with short description","Commons category link from Wikidata","Internet properties established in 2005","Newspaper companies of the United States","Newspapers published in San Francisco","Online publishing companies of the United States","Short description matches Wikidata","Technology blogs","Technology conferences","Use American English from December 2025","Use mdy dates from March 2024"],"url":"https://en.wikipedia.org/wiki/TechCrunch"}