{"docId":663,"title":"Chemical biology","body":"Chemical biology is a scientific discipline between the fields of chemistry and biology. The discipline involves the application of chemical techniques, analysis, and often small molecules produced through synthetic chemistry, to the study and manipulation of biological systems. Although often confused with biochemistry, which studies the chemistry of biomolecules and regulation of biochemical pathways within and between cells, chemical biology remains distinct by focusing on the application of chemical tools to address biological questions.","categories":["Articles with short description","Branches of biology","CS1: long volume value","Chemical biology","Chemistry","Induced stem cells","Short description is different from Wikidata","Use dmy dates from April 2016"],"url":"https://en.wikipedia.org/wiki/Chemical_biology"}