{"docId":6724,"title":"Reciprocity (electromagnetism)","body":"In classical electromagnetism, reciprocity refers to a variety of related theorems involving the interchange of time-harmonic electric current densities (sources) and the resulting electromagnetic fields in Maxwell's equations for time-invariant linear media under certain constraints. Reciprocity is closely related to the concept of symmetric operators from linear algebra, applied to electromagnetism.\nPerhaps the most common and general such theorem is Lorentz reciprocity (and its various special cases such as Rayleigh-Carson reciprocity),  named after work by Hendrik Lorentz in 1896 following analogous results regarding sound by Lord Rayleigh and light by Helmholtz (Potton 2004). Loosely, it states that the relationship between an oscillating current and the resulting electric field is unchanged if one interchanges the points where the current is placed and where the field is measured.  For the specific case of an electrical network, it is sometimes phrased as the statement that voltages and currents at different points in the network can be interchanged. More technically, it follows that the mutual impedance of a first circuit due to a second is the same as the mutual impedance of the second circuit due to the first.\nReciprocity is useful in optics, which (apart from quantum effects) can be expressed in terms of classical electromagnetism, but also in terms of radiometry.\nThere is also an analogous theorem in electrostatics, known as Green's reciprocity, relating the interchange of electric potential and electric charge density.\nForms of the reciprocity theorems are used in many electromagnetic applications, such as analyzing electrical networks and antenna systems.\nFor example, reciprocity implies that antennas work equally well as transmitters or receivers, and specifically that an antenna's radiation and receiving patterns are identical. Reciprocity is also a basic lemma that is used to prove other theorems about electromagnetic systems, such as the symmetry of the impedance matrix and scattering matrix, symmetries of Green's functions for use in boundary-element and transfer-matrix computational methods, as well as orthogonality properties of harmonic modes in waveguide systems (as an alternative to proving those properties directly from the symmetries of the eigen-operators).","categories":["All articles with unsourced statements","Articles with short description","Articles with unsourced statements from October 2014","CS1 maint: multiple names: authors list","Circuit theorems","Electromagnetism","Short description is different from Wikidata","Use dmy dates from August 2024"],"url":"https://en.wikipedia.org/wiki/Reciprocity_(electromagnetism)"}