{"docId":6943,"title":"Benjamin Bloom","body":"Benjamin Samuel Bloom (February 21, 1913 – September 13, 1999) was an American educational psychologist and didactician who made contributions to the classification of educational objectives and to the theory of mastery learning. He has greatly influenced the practices and philosophies of educators around the world from the latter part of the twentieth century.\nPerhaps his most significant contribution to the field of education was developing a comprehensive system of describing, assessing and classifying educational outcomes, now known as Bloom's taxonomy.","categories":["1913 births","1999 deaths","20th-century American educational theorists","20th-century American psychologists","American cognitive psychologists","American educational psychologists","Articles with hCards","Articles with short description","Pennsylvania State University alumni","People from Carbon County, Pennsylvania","Short description is different from Wikidata","University of Chicago alumni","University of Chicago faculty"],"url":"https://en.wikipedia.org/wiki/Benjamin_Bloom"}