{"docId":7726,"title":"Amenemhat IV","body":"See Amenemhat, for other individuals with this name.\nAmenemhat IV (also known as Amenemhet IV) was the seventh and penultimate king of the late Twelfth Dynasty of Egypt during the late Middle Kingdom period. He arguably ruled around 1786–1777 BC for about nine regnal years.\nAmenemhat IV may have been the son, grandson, son-in-law, or stepson of his predecessor, the powerful Amenemhat III. His reign started with a seemingly peaceful two-year coregency with Amenemhat III. He undertook expeditions in the Sinai for turquoise, in Upper Egypt for amethyst, and to the Land of Punt. He also maintained trade relations with Byblos as well as continuing the Egyptian presence in Nubia.\nAmenemhat IV built some parts of the temple of Hathor at Serabit el-Khadim in the Sinai, and constructed the well-preserved temple of Renenutet in Medinet Madi. The tomb of Amenemhat IV has not been identified, although the Southern Mazghuna pyramid is a possibility.\nAmenemhat IV was succeeded by Sobekneferu, who may have been his sister or stepsister; she was a daughter of Amenemhat III. Her reign marked the end of the Twelfth Dynasty and the beginning of the Middle Kingdom's decline into the Second Intermediate Period.","categories":["18th-century BC pharaohs","19th-century BC pharaohs","All accuracy disputes","Articles with disputed statements from February 2026","Articles with short description","Children of Amenemhat III","Commons category link from Wikidata","Good articles","Pages using the WikiHiero extension","Pharaohs of the Twelfth Dynasty of Egypt","Short description matches Wikidata","Use dmy dates from August 2022","Webarchive template wayback links"],"url":"https://en.wikipedia.org/wiki/Amenemhat_IV"}