{"docId":7876,"title":"Giorgio Parisi","body":"Giorgio Parisi (born 4 August 1948) is an Italian theoretical physicist, whose research has focused on quantum field theory, statistical mechanics and complex systems. His best known contributions are the QCD evolution equations for parton densities, obtained with Guido Altarelli, known as the Altarelli–Parisi or DGLAP equations, the exact solution of the Sherrington–Kirkpatrick model of spin glasses, the Kardar–Parisi–Zhang equation describing dynamic scaling of growing interfaces, and the study of whirling flocks of birds. He was awarded the 2021 Nobel Prize in Physics jointly with Klaus Hasselmann and Syukuro Manabe for groundbreaking contributions to theory of complex systems, in particular \"for the discovery of the interplay of disorder and fluctuations in physical systems from atomic to planetary scales\".","categories":["1948 births","20th-century Italian physicists","21st-century Italian physicists","Academic staff of the Sapienza University of Rome","Academic staff of the University of Rome Tor Vergata","Articles with Italian-language sources (it)","Articles with hCards","Articles with short description","Biography articles needing translation from Italian Wikipedia","CS1 Italian-language sources (it)","CS1 maint: deprecated archival service","Columbia University faculty","Foreign associates of the National Academy of Sciences","Italian Freemasons","Italian Nobel laureates","Italian mathematical physicists","Italian theoretical physicists","Knights Grand Cross of the Order of Merit of the Italian Republic","Living people","Members of the American Philosophical Society"],"url":"https://en.wikipedia.org/wiki/Giorgio_Parisi"}