{"docId":8135,"title":"American and British English spelling differences","body":"Despite the various English dialects spoken from country to country and within different regions of the same country, there are only slight regional variations in English orthography, the two most notable variations being British and American spelling. Many of the differences between American and British or Commonwealth English date back to a time before spelling standards were developed. For instance, some spellings seen as \"American\" were once commonly used in the United Kingdom, and some spellings seen as \"British\" were once commonly used in the United States.\nA \"British standard\" began to emerge following the 1755 publication of Samuel Johnson's A Dictionary of the English Language, and an \"American standard\" started following the work of Noah Webster and, in particular, his An American Dictionary of the English Language, first published in 1828. Webster's efforts at spelling reform were effective in his native country, resulting in certain well-known patterns of spelling differences between the American and British varieties of English.","categories":["All articles with dead external links","All articles with unsourced statements","American and British English differences","Articles containing Ancient Greek (to 1453)-language text","Articles containing Anglo-Norman-language text","Articles containing Classical Nahuatl-language text","Articles containing French-language text","Articles containing Greek-language text","Articles containing Latin-language text","Articles containing Middle English (1100-1500)-language text","Articles containing Old English (ca. 450-1100)-language text","Articles containing Old French (842-ca. 1400)-language text","Articles containing Spanish-language text","Articles containing Turkish-language text","Articles containing explicitly cited American English-language text","Articles containing explicitly cited British English-language text","Articles with dead external links from September 2022","Articles with short description","Articles with unsourced statements from August 2008","Articles with unsourced statements from August 2025"],"url":"https://en.wikipedia.org/wiki/American_and_British_English_spelling_differences"}