{"docId":9270,"title":"Hantaro Nagaoka","body":"Hantaro Nagaoka (長岡 半太郎, Nagaoka Hantarō; August 19, 1865 – December 11, 1950) was a Japanese physicist and a pioneer of Japanese physics during the Meiji period.","categories":["1865 births","1950 deaths","20th-century Japanese physicists","Academic staff of Osaka University","Academic staff of the University of Tokyo","Articles containing Japanese-language text","Articles with hCards","Articles with short description","CS1 Japanese-language sources (ja)","Fellows of the American Physical Society","Honorary members of the USSR Academy of Sciences","Japanese theoretical physicists","Kaisei Academy alumni","Members of the Japan Academy","Recipients of the Order of Culture","Riken personnel","Scientists from Nagasaki Prefecture","Short description matches Wikidata","University of Tokyo alumni"],"url":"https://en.wikipedia.org/wiki/Hantaro_Nagaoka"}