{"docId":996,"title":"Computer cartography","body":"Computer cartography (also called digital cartography) is the art, science, and technology of making and using maps with a computer. This technology represents a paradigm shift in how maps are produced, but is still fundamentally a subset of traditional cartography. The primary function of this technology is to produce maps, including creation of accurate representations of a particular area such as, detailing major road arteries and other points of interest for navigation, and in the creation of thematic maps. Computer cartography is one of the main functions of geographic information systems (GIS), however, GIS is not necessary to facilitate computer cartography and has functions beyond just making maps. The first peer-reviewed publications on using computers to help in the cartographic process predate the introduction of full GIS by several years.\nComputer cartography is employed to facilitate a variety of computer applications, often through integration with the Global Positioning System (GPS) satellite network. This can allow real-time automated map generation for tasks such as automotive navigation systems.","categories":["All articles containing potentially dated statements","All articles with unsourced statements","Articles containing potentially dated statements from 2009","Articles with short description","Articles with unsourced statements from September 2018","Digital mapping","Geodesy","Short description is different from Wikidata","Webarchive template wayback links"],"url":"https://en.wikipedia.org/wiki/Computer_cartography"}