{"docId":9988,"title":"Dance","body":"Dance is an art form, consisting of sequences of body movements with aesthetic and often symbolic value, either improvised or purposefully selected. Dance can be categorized and described by its choreography, by its repertoire of movements or by its historical period or place of origin. Dance is typically performed with musical accompaniment, and sometimes with the dancer simultaneously using a musical instrument themselves.\nTwo common types of group dance are theatrical and participatory dance. Both types of dance may have special functions, whether social, ceremonial, competitive, erotic, martial, sacred or liturgical. Dance is not solely restricted to performance, as dance is used as a form of exercise and occasionally training for other sports and activities. Dance performances and dancing competitions are found across the world exhibiting various different styles and standards.\nDance may also be participated in alone as a form of exercise or self expression. Dancing is common human behaviour, and does not necessarily require specific choreography.","categories":["All articles needing additional references","All articles with style issues","Articles containing suspected AI-generated texts from August 2025","Articles containing video clips","Articles needing additional references from March 2025","Articles with multiple maintenance issues","Articles with short description","CS1 Chinese-language sources (zh)","CS1 maint: location missing publisher","CS1 maint: others","Dance","Entertainment occupations","Pages using Sister project links with default search","Pages using Sister project links with hidden wikidata","Performing arts","Short description is different from Wikidata","Theatrical occupations","Webarchive template wayback links","Wikipedia articles incorporating a citation from the 1911 Encyclopaedia Britannica with Wikisource reference","Wikipedia articles with style issues from June 2023"],"url":"https://en.wikipedia.org/wiki/Dance"}